setup.py
distributions_nik/Binomialdistribution.py
distributions_nik/Gaussiandistribution.py
distributions_nik/Generaldistribution.py
distributions_nik/__init__.py
distributions_nik.egg-info/PKG-INFO
distributions_nik.egg-info/SOURCES.txt
distributions_nik.egg-info/dependency_links.txt
distributions_nik.egg-info/not-zip-safe
distributions_nik.egg-info/top_level.txt