Metadata-Version: 1.0
Name: distributions-nik
Version: 1.2
Summary: Gaussian and Binomial distributions
Home-page: UNKNOWN
Author: niks_2708
Author-email: UNKNOWN
License: UNKNOWN
Platform: UNKNOWN
